term_timer/__init__.py
term_timer/aggregator.py
term_timer/argparser.py
term_timer/arguments.py
term_timer/config.py
term_timer/constants.py
term_timer/formatter.py
term_timer/importers.py
term_timer/in_out.py
term_timer/logger.py
term_timer/magic_cube.py
term_timer/manage.py
term_timer/scrambler.py
term_timer/solve.py
term_timer/stats.py
term_timer/timer.py
term_timer/trainer.py
term_timer/transform.py
term_timer/triggers.py
term_timer-0.1.0.dist-info/licenses/LICENSE
term_timer-0.1.0.dist-info/METADATA
term_timer-0.1.0.dist-info/WHEEL
term_timer-0.1.0.dist-info/entry_points.txt
term_timer-0.1.0.dist-info/top_level.txt
term_timer-0.1.0.dist-info/RECORD
