Metadata-Version: 2.4
Name: term-timer
Version: 0.1.0
Summary: Speed Cubing Timer on your Terminal
Requires-Python: >=3.9
License-File: LICENSE
Requires-Dist: magiccube==1.2.0
Requires-Dist: plotext==5.3.2
Requires-Dist: rich==13.9.4
Requires-Dist: bleak==1.1.0
Requires-Dist: Jinja2==3.1.6
Requires-Dist: bottle==0.13.3
Requires-Dist: cryptography==44.0.2
Requires-Dist: kociemba==1.2.1
Requires-Dist: cubing_algs==1.0.0
Provides-Extra: dev
Requires-Dist: ruff==0.11.12; extra == "dev"
Requires-Dist: mypy==1.16.0; extra == "dev"
Requires-Dist: pytest==8.3.5; extra == "dev"
Requires-Dist: pytest-cov==6.1.1; extra == "dev"
Dynamic: license-file
